spechub/__init__.py
spechub-0.0.1.dist-info/METADATA
spechub-0.0.1.dist-info/WHEEL
spechub-0.0.1.dist-info/RECORD
