Metadata-Version: 2.4
Name: spechub
Version: 0.0.1
Summary: Spechub
Project-URL: Homepage, https://spechub.com
Author: Matt Holden
Requires-Python: >=3.8
